MANIFEST.in
setup.py
wagtail_site/__init__.py
wagtail_site/manage.py
wagtail_site.egg-info/PKG-INFO
wagtail_site.egg-info/SOURCES.txt
wagtail_site.egg-info/dependency_links.txt
wagtail_site.egg-info/requires.txt
wagtail_site.egg-info/top_level.txt
wagtail_site/home/__init__.py
wagtail_site/home/models.py
wagtail_site/home/migrations/0001_initial.py
wagtail_site/home/migrations/0002_create_homepage.py
wagtail_site/home/migrations/__init__.py
wagtail_site/home/static/css/welcome_page.css
wagtail_site/home/templates/home/home_page.html
wagtail_site/home/templates/home/welcome_page.html
wagtail_site/search/__init__.py
wagtail_site/search/views.py
wagtail_site/wagtail_site/__init__.py
wagtail_site/wagtail_site/urls.py
wagtail_site/wagtail_site/wsgi.py
wagtail_site/wagtail_site/settings/__init__.py
wagtail_site/wagtail_site/settings/base.py
wagtail_site/wagtail_site/settings/dev.py
wagtail_site/wagtail_site/settings/production.py
wagtail_site/wagtail_site/templates/404.html
wagtail_site/wagtail_site/templates/500.html
wagtail_site/wagtail_site/templates/base.html