Metadata-Version: 1.0
Name: wagtail-site
Version: 1.1
Summary: web wagtail site
Home-page: UNKNOWN
Author: Alexandro.by
Author-email: alexander.ermak@celadon.ae
License: MIT
Platform: UNKNOWN
